{"status":{"code":200,"http":"Fetched (ring) 200 450 and parsed 1/36 entries","nextFetch":1505772,"entriesCountSinceLastMaintenance":4,"velocity":12.8,"popularity":1.691917961214445,"generatedIds":true,"period":450,"lastFetch":1505771,"lastParse":1505771,"lastMaintenanceAt":1505753,"feed":"http://azbigmedia.com/feed"},"standardLinks":{"https://api.w.org/":[{"rel":"https://api.w.org/","href":"http://azbigmedia.com/wp-json/"}],"self":[{"title":"AZ Big Media","rel":"self","href":"http://azbigmedia.com/feed/","type":"application/rss+xml"}],"alternate":[{"title":"AZ Big Media","rel":"alternate","href":"http://azbigmedia.com","type":"text/html"}]},"permalinkUrl":"http://azbigmedia.com","title":"AZ Big Media","updated":1505771411,"id":"az-big-media-2017-9-18-21","items":[{"id":"http://azbigmedia.com/?p=201783","published":1505771411,"updated":1505771411,"title":"Los Sombreros in Scottsdale shows history does repeat itself","summary":"<p>Los Sombreros co-owners Kurt Riske and Geoff Schuman know a thing or two about the restaurant industry with a combined 25 years’ experience, but in acquiring the South Scottsdale restaurant, it is their history with the establishment that really resonates. Both Riske and Schuman started their respective career paths working as servers and bartenders in the early 2000’s and are now honoring the tradition of Los Sombreros while updating it to meet the expectations of!</p>\n<p>The post <a rel=\"nofollow\" href=\"http://azbigmedia.com/los-sombreros-scottsdale-shows-history-repeat/\">Los Sombreros in Scottsdale shows history does repeat itself</a> appeared first on <a rel=\"nofollow\" href=\"http://azbigmedia.com\">AZ Big Media</a>.</p>","permalinkUrl":"http://azbigmedia.com/los-sombreros-scottsdale-shows-history-repeat/","standardLinks":{"alternate":[{"title":"Los Sombreros in Scottsdale shows history does repeat itself","rel":"alternate","href":"http://azbigmedia.com/los-sombreros-scottsdale-shows-history-repeat/","type":"text/html"}]},"actor":{"displayName":"Experience AZ","id":"Experience AZ"},"categories":["Lifestyle","Restaurants"],"language":"en"}]}