{"status":{"code":200,"http":"Fetched (ring) 200 450 and parsed 1/36 entries","nextFetch":1505777,"entriesCountSinceLastMaintenance":6,"velocity":12.8,"popularity":1.691917961214445,"generatedIds":true,"period":450,"lastFetch":1505776,"lastParse":1505776,"lastMaintenanceAt":1505753,"feed":"http://azbigmedia.com/feed"},"standardLinks":{"https://api.w.org/":[{"rel":"https://api.w.org/","href":"http://azbigmedia.com/wp-json/"}],"self":[{"title":"AZ Big Media","rel":"self","href":"http://azbigmedia.com/feed/","type":"application/rss+xml"}],"alternate":[{"title":"AZ Big Media","rel":"alternate","href":"http://azbigmedia.com","type":"text/html"}]},"permalinkUrl":"http://azbigmedia.com","title":"AZ Big Media","updated":1505776205,"id":"az-big-media-2017-9-18-23","items":[{"id":"http://azbigmedia.com/?p=201803","published":1505776205,"updated":1505776205,"title":"Western Wealth Capital sells Tempe apartments for $25.7 million","summary":"<p>Cushman &#38; Wakefield completed the sale of Anzio Apartment Homes, located at 1330 West Broadway Road in Tempe, Arizona. An entity formed by Laguna Point Properties, LLC of Laguna Hills, California purchased the property from WWC VII, LLC, a company formed by Western Wealth Capital of North Vancouver, British Columbia, for $25.7 million. David Fogler and Steven Nicoluzakis of Cushman &#38; Wakefield represented the seller. Anzio Apartment Homes is a 240-unit, Class B garden-style apartment!</p>\n<p>The post <a rel=\"nofollow\" href=\"http://azbigmedia.com/western-wealth-capital-sells-tempe-apartments-25-7-million/\">Western Wealth Capital sells Tempe apartments for $25.7 million</a> appeared first on <a rel=\"nofollow\" href=\"http://azbigmedia.com\">AZ Big Media</a>.</p>","permalinkUrl":"http://azbigmedia.com/western-wealth-capital-sells-tempe-apartments-25-7-million/","standardLinks":{"alternate":[{"title":"Western Wealth Capital sells Tempe apartments for $25.7 million","rel":"alternate","href":"http://azbigmedia.com/western-wealth-capital-sells-tempe-apartments-25-7-million/","type":"text/html"}]},"actor":{"displayName":"AZRE","id":"AZRE"},"categories":["Real Estate","Big Deals","Multifamily"],"language":"en"}]}