{"status":{"code":200,"http":"Fetched (ping) 200 3434 and parsed 1/60 entries","nextFetch":1505840,"entriesCountSinceLastMaintenance":60,"velocity":36.1,"popularity":3.1448282277748527,"generatedIds":true,"period":3434,"lastFetch":1505836,"lastParse":1505836,"lastMaintenanceAt":1505760,"feed":"http://feeds.sciencedaily.com/sciencedaily"},"permalinkUrl":"https://www.sciencedaily.com/news/","standardLinks":{"alternate":[{"title":"Latest Science News -- ScienceDaily","rel":"alternate","href":"https://www.sciencedaily.com/news/","type":"text/html"}],"image":[{"title":"Latest Science News -- ScienceDaily","rel":"image","href":"https://www.sciencedaily.com/images/scidaily-logo-rss.png","type":"image/png"}],"hub":[{"title":"","rel":"hub","href":"http://pubsubhubbub.appspot.com/","type":"text/html"}],"self":[{"title":"Latest Science News -- ScienceDaily","rel":"self","href":"http://www.sciencedaily.com/rss/newsfeed.xml","type":"application/rss+xml"}]},"image":"https://www.sciencedaily.com/images/scidaily-logo-rss.png","title":"Latest Science News -- ScienceDaily","updated":1505836442,"id":"latest-science-news-sciencedaily-2017-9-19-15","items":[{"id":"https://www.sciencedaily.com/releases/2017/09/170919110607.htm","published":1505833567,"updated":1505833567,"title":"Contribution of opioid-related deaths to the change in life expectancy in the US","summary":"Between 2000 and 2015 in the US, life expectancy increased overall but drug-poisoning deaths, mostly related to opioids, contributed to reducing life expectancy, according to a study.","permalinkUrl":"https://www.sciencedaily.com/releases/2017/09/170919110607.htm","standardLinks":{"alternate":[{"title":"Contribution of opioid-related deaths to the change in life expectancy in the US","rel":"alternate","href":"https://www.sciencedaily.com/releases/2017/09/170919110607.htm","type":"text/html"}]},"language":"en"}]}