{"status":{"code":200,"http":"Fetched (ping) 200 450 and parsed 1/36 entries","nextFetch":1505837,"entriesCountSinceLastMaintenance":12,"velocity":12.8,"popularity":1.691917961214445,"generatedIds":true,"period":450,"lastFetch":1505836,"lastParse":1505836,"lastMaintenanceAt":1505753,"feed":"http://azbigmedia.com/feed"},"standardLinks":{"https://api.w.org/":[{"rel":"https://api.w.org/","href":"http://azbigmedia.com/wp-json/"}],"self":[{"title":"AZ Big Media","rel":"self","href":"http://azbigmedia.com/feed/","type":"application/rss+xml"}],"alternate":[{"title":"AZ Big Media","rel":"alternate","href":"http://azbigmedia.com","type":"text/html"}]},"permalinkUrl":"http://azbigmedia.com","title":"AZ Big Media","updated":1505836204,"id":"az-big-media-2017-9-19-15","items":[{"id":"http://azbigmedia.com/?p=201815","published":1505836204,"updated":1505836204,"title":"On the move at NAI Horizon, Fidelity National Title, JHC","summary":"<p>NAI Horizon hires Sarah Stecko as marketing specialist NAI Horizon, celebrating 25 years in the Valley, continues its growth in Arizona with the hiring of Sarah Stecko as Marketing Specialist. Stecko will collaborate with the brokerage teams to provide coordination and creation of consistently-branded marketing materials. This includes proposals, database support, and preparation of accurate, timely, and relevant documentation. Stecko comes to NAI Horizon after three years as Editor in Chief of Commercial Executive Magazine!</p>\n<p>The post <a rel=\"nofollow\" href=\"http://azbigmedia.com/move-nai-horizon-fidelity-national-title-jhc/\">On the move at NAI Horizon, Fidelity National Title, JHC</a> appeared first on <a rel=\"nofollow\" href=\"http://azbigmedia.com\">AZ Big Media</a>.</p>","permalinkUrl":"http://azbigmedia.com/move-nai-horizon-fidelity-national-title-jhc/","standardLinks":{"alternate":[{"title":"On the move at NAI Horizon, Fidelity National Title, JHC","rel":"alternate","href":"http://azbigmedia.com/move-nai-horizon-fidelity-national-title-jhc/","type":"text/html"}]},"actor":{"displayName":"AZ Business Leaders","id":"AZ Business Leaders"},"categories":["Business News","Business Leaders","Newsmakers"],"language":"en"}]}